optom_automator/__init__.py
optom_automator/__main__.py
optom_automator/main.py
optom_automator/phrases/__init__.py
optom_automator/phrases/exceptions.py
optom_automator/phrases/phrase_tree.py
optom_automator/phrases/phrases.py
optom_automator/phrases/types.py
optom_automator/reader/__init__.py
optom_automator/reader/exceptions.py
optom_automator/reader/reader.py
optom_automator/utils/__init__.py
optom_automator/utils/logger.py
optom_automator-0.4.1.dist-info/LICENSE
optom_automator-0.4.1.dist-info/METADATA
optom_automator-0.4.1.dist-info/WHEEL
optom_automator-0.4.1.dist-info/entry_points.txt
optom_automator-0.4.1.dist-info/top_level.txt
optom_automator-0.4.1.dist-info/RECORD
